pattern_sort/__init__.py
pattern_sort/pattern.py
pattern_sort/sort.py
pattern_sort_package-1.0.3.dist-info/LICENSE.txt
pattern_sort_package-1.0.3.dist-info/METADATA
pattern_sort_package-1.0.3.dist-info/WHEEL
pattern_sort_package-1.0.3.dist-info/top_level.txt
pattern_sort_package-1.0.3.dist-info/RECORD
