Metadata-Version: 2.1
Name: pattern_sort_package
Version: 1.0.3
Summary: A Python package for pattern generation and sorting algorithms.
Home-page: https://github.com/abuawaish/awaish_pkg
Author: Abu Awaish
Author-email: abuawaish7@gmail.com
License: MIT
Keywords: funny
Classifier: Programming Language :: Python :: 3
Classifier: License :: OSI Approved :: MIT License
Classifier: Operating System :: OS Independent
Requires-Python: >=3.6
License-File: LICENSE.txt
